markdown_worker/__init__.py
markdown_worker/markdown_worker.py
markdown_worker-0.0.4.dist-info/LICENSE
markdown_worker-0.0.4.dist-info/METADATA
markdown_worker-0.0.4.dist-info/WHEEL
markdown_worker-0.0.4.dist-info/top_level.txt
markdown_worker-0.0.4.dist-info/RECORD
