Metadata-Version: 2.2
Name: markdown-worker
Version: 0.0.4
Summary: A simple markdown parsing package.
Author: Mantresh Khurana
Author-email: <mantreshkhurana@spyxpo.com>
Keywords: python,mantresh khurana,parser,markdown
Classifier: Development Status :: 1 - Planning
Classifier: Intended Audience :: Developers
Classifier: Programming Language :: Python :: 3
Classifier: Operating System :: Unix
Classifier: Operating System :: MacOS :: MacOS X
Classifier: Operating System :: Microsoft :: Windows
License-File: LICENSE
Requires-Dist: numpy
Dynamic: author
Dynamic: author-email
Dynamic: classifier
Dynamic: description
Dynamic: description-content-type
Dynamic: keywords
Dynamic: requires-dist
Dynamic: summary
